EVM.srcs/sources_1/new/ElectronicsVotingMachine.v
`timescale 1ns / 1ps

module buttonControl(
input clock,
input reset,
input button,
output reg valid_vote
);

reg [30:0] counter;

always @(posedge clock)
begin
    if(reset)
        counter <= 0;
        else
        begin
            if(button & counter <11)
                counter <= counter + 1;
            else if(button)
                counter <= 0;
        end
end

always @(posedge clock)
begin
    if(reset)
        valid_vote <= 1'b0;
    else
    begin
        if(counter == 10)
            valid_vote <= 1'b1;
        else
            valid_vote <= 1'b0;
    end
end
endmodule

module ModuleControl(
input clock,
input reset,
input mode,
input valid_vote_casted,
input [7:0] candidate1_vote,
input [7:0] candidate2_vote,
input [7:0] candidate3_vote,
input [7:0] candidate4_vote,
input candidate1_button_press,
input candidate2_button_press,
input candidate3_button_press,
input candidate4_button_press,
output reg [7:0] leds
);

reg [30:0] counter;

always @(posedge clock)
begin
    if(reset)
        counter <= 0; // whenever reset passes so coumter start from 0
    else if(valid_vote_casted) // if valid vote is casted then counter becomes 1
        counter <= counter + 1;
    else if(counter != 0 & counter < 10)
        counter <= counter + 1;
    else
        counter <= 0;
end

always @(posedge clock)
begin
    if(reset)
        leds <= 0;
    else
    begin
        if(mode == 0 & counter>0) //mode0 --> voting mode
            leds <= 8'hFF;
        else if(mode == 0)
            leds  <= 8'h00;
        else if(mode == 1) //mode1 --> Result Mode
        begin
            if(candidate1_button_press)
                leds <= candidate1_vote;
            else if(candidate2_button_press)
                leds <= candidate2_vote;
            else if(candidate3_button_press)
                leds <= candidate3_vote;
            else if(candidate4_button_press)
                leds <= candidate4_vote;
            end
       end
end

endmodule

module VoteLogger(
input clock,
input reset,
input mode,
input cand1_vote_valid,
input cand2_vote_valid,
input cand3_vote_valid,
input cand4_vote_valid,
output reg [7:0] cand1_vote_recvd,
output reg [7:0] cand2_vote_recvd,
output reg [7:0] cand3_vote_recvd,
output reg [7:0] cand4_vote_recvd
);

always @(posedge clock)
begin   
    if(reset)
    begin
        cand1_vote_recvd <= 0;
        cand2_vote_recvd <= 0;
        cand3_vote_recvd <= 0;
        cand4_vote_recvd <= 0;
    end
    else
    begin
        if(cand1_vote_valid & mode == 0)
            cand1_vote_recvd <= cand1_vote_recvd + 1;
        else if(cand2_vote_valid & mode == 0)
            cand2_vote_recvd <= cand2_vote_recvd + 1;
        else if(cand3_vote_valid & mode == 0)
            cand3_vote_recvd <= cand3_vote_recvd + 1;
        else if(cand4_vote_valid & mode == 0)
            cand4_vote_recvd <= cand4_vote_recvd + 1;            
     end
end

endmodule        

module VotingMachine(
input clock,
input reset,
input mode,
input button1,
input button2,
input button3,
input button4,
output [7:0] led
);

wire valid_vote_1;
wire valid_vote_2;
wire valid_vote_3;
wire valid_vote_4;
wire [7:0] cand1_vote_recvd;
wire [7:0] cand2_vote_recvd;            
wire [7:0] cand3_vote_recvd;
wire [7:0] cand4_vote_recvd;
wire anyValidVote;

assign anyValidVote = valid_vote_1 | valid_vote_2 | valid_vote_3 | valid_vote_4;

buttonControl bc1(
.clock(clock),
.reset(reset),
.button(button1),
.valid_vote(valid_vote_1)
);

buttonControl bc2(
.clock(clock),
.reset(reset),
.button(button2),
.valid_vote(valid_vote_2)
);

buttonControl bc3(
.clock(clock),
.reset(reset),
.button(button3),
.valid_vote(valid_vote_3)
);

buttonControl bc4(
.clock(clock),
.reset(reset),
.button(button4),
.valid_vote(valid_vote_4)
);

VoteLogger VL(
.clock(clock),
.reset(reset),
.mode(mode),
.cand1_vote_valid(valid_vote_1),
.cand2_vote_valid(valid_vote_2),
.cand3_vote_valid(valid_vote_3),
.cand4_vote_valid(valid_vote_4),
.cand1_vote_recvd(cand1_vote_recvd),
.cand2_vote_recvd(cand2_vote_recvd),
.cand3_vote_recvd(cand3_vote_recvd),
.cand4_vote_recvd(cand4_vote_recvd)
);

ModuleControl MC(
.clock(clock),
.reset(reset),
.mode(mode),
.valid_vote_casted(anyValidVote),
.candidate1_vote(cand1_vote_recvd),
.candidate2_vote(cand2_vote_recvd),
.candidate3_vote(cand3_vote_recvd),
.candidate4_vote(cand4_vote_recvd),
.candidate1_button_press(valid_vote_1),
.candidate2_button_press(valid_vote_2),
.candidate3_button_press(valid_vote_3),
.candidate4_button_press(valid_vote_4),
.leds(led)
);

endmodule

EVM.srcs/sim_1/new/EVM_Test_Bench.v
`timescale 1ns / 1ps
module test;

    // Inputs
    reg clock;
    reg reset;
    reg mode;
    reg button1;
    reg button2;
    reg button3;
    reg button4;
    
    //Outputs
    wire [7:0] led;
    
    // Instantiate the Unit Under Test (UUT)
    VotingMachine uut(
    .clock(clock),
    .reset(reset),
    .mode(mode),
    .button1(button1),
    .button2(button2),
    .button3(button3),
    .button4(button4),
    .led(led)
    );
    
    initial begin
        clock = 0;
        forever #5 clock = ~clock;
    end
    
    initial begin
        // initialize the inputs
        reset = 1;
        mode = 0;
        button1 = 0;
        button2 = 0;
        button3 = 0;
        button4 = 0;
        
        // Will wait for global reset
        #100
        
        #100 reset = 0; mode = 0; button1 = 0; button2 = 0; button3 = 0; button4 = 0;
        #5 reset = 0; mode = 0; button1 = 1; button2 = 0; button3 = 0; button4 = 0;
        #10 reset = 0; mode = 0; button1 = 0; button2 = 0; button3 = 0; button4 = 0;
        #5 reset = 0; mode = 0; button1 = 1; button2 = 0; button3 = 0; button4 = 0;
        #200 reset = 0; mode = 0; button1 = 0; button2 = 0; button3 = 0; button4 = 0;
        #5 reset = 0; mode = 0; button1 = 0; button2 = 0; button3 = 0; button4 = 0;
        #10 reset = 0; mode = 0; button1 = 0; button2 = 0; button3 = 0; button4 = 0;
        #5 reset = 0; mode = 0; button1 = 0; button2 = 0; button3 = 0; button4 = 0;
        
        
        
        #5 reset = 0; mode = 0; button1 = 0; button2 = 1; button3 = 0; button4 = 0;
        #200 reset = 0; mode = 0; button1 = 0; button2 = 0; button3 = 0; button4 = 0;
        #5 reset = 0; mode = 0; button1 = 0; button2 = 0; button3 = 0; button4 = 0;
        #10 reset = 0; mode = 0; button1 = 0; button2 = 0; button3 = 0; button4 = 0;
        #5 reset = 0; mode = 0; button1 = 0; button2 = 0; button3 = 0; button4 = 0;       
        
        
        
        #5 reset = 0; mode = 0; button1 = 0; button2 = 1; button3 = 1; button4 = 0;
        #200 reset = 0; mode = 0; button1 = 0; button2 = 0; button3 = 0; button4 = 0;
        #5 reset = 0; mode = 0; button1 = 0; button2 = 0; button3 = 0; button4 = 0;
        #10 reset = 0; mode = 0; button1 = 0; button2 = 0; button3 = 0; button4 = 0;
        #5 reset = 0; mode = 0; button1 = 0; button2 = 0; button3 = 0; button4 = 0; 
        
        
        
        #5 reset = 0; mode = 1; button1 = 0; button2 = 1; button3 = 0; button4 = 0;
        #200 reset = 0; mode = 1; button1 = 0; button2 = 0; button3 = 1; button4 = 0;
        #5 reset = 0; mode = 0; button1 = 0; button2 = 0; button3 = 0; button4 = 0;
        #10 reset = 0; mode = 0; button1 = 0; button2 = 0; button3 = 0; button4 = 0;
        #5 reset = 0; mode = 0; button1 = 0; button2 = 0; button3 = 0; button4 = 0;        
        
        
        
        #5 reset = 0; mode = 0; button1 = 0; button2 = 0; button3 = 1; button4 = 0;
        #200 reset = 0; mode = 0; button1 = 0; button2 = 0; button3 = 0; button4 = 0;
        #5 reset = 0; mode = 0; button1 = 0; button2 = 0; button3 = 0; button4 = 0;
        #10 reset = 0; mode = 0; button1 = 0; button2 = 0; button3 = 0; button4 = 0;
        #5 reset = 0; mode = 0; button1 = 0; button2 = 0; button3 = 0; button4 = 0;
        
         
        $stop; 
    end   
     
     // Dump waveform data for GTKWave or any simulator
    initial 
        begin
        $dumpvars;
            $dumpfile("dump.vcd");   // name of the waveform file
            
    end

// Monitor signals during simulation
    initial begin
    $monitor($time, " mode = %b, button1 = %b, button2 = %b, button3 = %b, button4 = %b, led = %d", 
             mode, button1, button2, button3, button4, led);
    end
    
endmodule

EVM.sim/sim_1/behav/xsim/dump.vcd
$date
   Thu Aug 21 19:19:57 2025
$end

$version
  2024.1
$end

$timescale
  1ps
$end

$scope module test $end
$var reg 1 ! clock $end
$var reg 1 " reset $end
$var reg 1 # mode $end
$var reg 1 $ button1 $end
$var reg 1 % button2 $end
$var reg 1 & button3 $end
$var reg 1 ' button4 $end
$var wire 8 ( led [7:0] $end
$scope module uut $end
$var wire 1 ) clock $end
$var wire 1 * reset $end
$var wire 1 + mode $end
$var wire 1 , button1 $end
$var wire 1 - button2 $end
$var wire 1 . button3 $end
$var wire 1 / button4 $end
$var wire 8 ( led [7:0] $end
$var wire 1 0 valid_vote_1 $end
$var wire 1 1 valid_vote_2 $end
$var wire 1 2 valid_vote_3 $end
$var wire 1 3 valid_vote_4 $end
$var wire 8 4 cand1_vote_recvd [7:0] $end
$var wire 8 5 cand2_vote_recvd [7:0] $end
$var wire 8 6 cand3_vote_recvd [7:0] $end
$var wire 8 7 cand4_vote_recvd [7:0] $end
$var wire 1 8 anyValidVote $end
$scope module bc1 $end
$var wire 1 ) clock $end
$var wire 1 * reset $end
$var wire 1 , button $end
$var reg 1 9 valid_vote $end
$var reg 31 : counter [30:0] $end
$upscope $end
$scope module bc2 $end
$var wire 1 ) clock $end
$var wire 1 * reset $end
$var wire 1 - button $end
$var reg 1 ; valid_vote $end
$var reg 31 < counter [30:0] $end
$upscope $end
$scope module bc3 $end
$var wire 1 ) clock $end
$var wire 1 * reset $end
$var wire 1 . button $end
$var reg 1 = valid_vote $end
$var reg 31 > counter [30:0] $end
$upscope $end
$scope module bc4 $end
$var wire 1 ) clock $end
$var wire 1 * reset $end
$var wire 1 / button $end
$var reg 1 ? valid_vote $end
$var reg 31 @ counter [30:0] $end
$upscope $end
$scope module VL $end
$var wire 1 ) clock $end
$var wire 1 * reset $end
$var wire 1 + mode $end
$var wire 1 0 cand1_vote_valid $end
$var wire 1 1 cand2_vote_valid $end
$var wire 1 2 cand3_vote_valid $end
$var wire 1 3 cand4_vote_valid $end
$var reg 8 A cand1_vote_recvd [7:0] $end
$var reg 8 B cand2_vote_recvd [7:0] $end
$var reg 8 C cand3_vote_recvd [7:0] $end
$var reg 8 D cand4_vote_recvd [7:0] $end
$upscope $end
$scope module MC $end
$var wire 1 ) clock $end
$var wire 1 * reset $end
$var wire 1 + mode $end
$var wire 1 8 valid_vote_casted $end
$var wire 8 4 candidate1_vote [7:0] $end
$var wire 8 5 candidate2_vote [7:0] $end
$var wire 8 6 candidate3_vote [7:0] $end
$var wire 8 7 candidate4_vote [7:0] $end
$var wire 1 0 candidate1_button_press $end
$var wire 1 1 candidate2_button_press $end
$var wire 1 2 candidate3_button_press $end
$var wire 1 3 candidate4_button_press $end
$var reg 8 E leds [7:0] $end
$var reg 31 F counter [30:0] $end
$upscope $end
$upscope $end
$upscope $end
$enddefinitions $end

#0
$dumpvars
0!
1"
0#
0$
0%
0&
0'
bx (
0)
1*
0+
0,
0-
0.
0/
x0
x1
x2
x3
bx 4
bx 5
bx 6
bx 7
x8
x9
bx :
x;
bx <
x=
bx >
x?
bx @
bx A
bx B
bx C
bx D
bx E
bx F
$end

#5000
1!
b0 (
1)
00
01
02
03
b0 4
b0 5
b0 6
b0 7
08
09
b0 :
0;
b0 <
0=
b0 >
0?
b0 @
b0 A
b0 B
b0 C
b0 D
b0 E
b0 F

#10000
0!
0)

#15000
1!
1)

#20000
0!
0)

#25000
1!
1)

#30000
0!
0)

#35000
1!
1)

#40000
0!
0)

#45000
1!
1)

#50000
0!
0)

#55000
1!
1)

#60000
0!
0)

#65000
1!
1)

#70000
0!
0)

#75000
1!
1)

#80000
0!
0)

#85000
1!
1)

#90000
0!
0)

#95000
1!
1)

#100000
0!
0)

#105000
1!
1)

#110000
0!
0)

#115000
1!
1)

#120000
0!
0)

#125000
1!
1)

#130000
0!
0)

#135000
1!
1)

#140000
0!
0)

#145000
1!
1)

#150000
0!
0)

#155000
1!
1)

#160000
0!
0)

#165000
1!
1)

#170000
0!
0)

#175000
1!
1)

#180000
0!
0)

#185000
1!
1)

#190000
0!
0)

#195000
1!
1)

#200000
0!
0"
0)
0*

#205000
1!
1$
1)
1,
b1 :

#210000
0!
0)

#215000
1!
0$
1)
0,

#220000
0!
1$
0)
1,

#225000
1!
1)
b10 :

#230000
0!
0)

#235000
1!
1)
b11 :

#240000
0!
0)

#245000
1!
1)
b100 :

#250000
0!
0)

#255000
1!
1)
b101 :

#260000
0!
0)

#265000
1!
1)
b110 :

#270000
0!
0)

#275000
1!
1)
b111 :

#280000
0!
0)

#285000
1!
1)
b1000 :

#290000
0!
0)

#295000
1!
1)
b1001 :

#300000
0!
0)

#305000
1!
1)
b1010 :

#310000
0!
0)

#315000
1!
1)
10
18
19
b1011 :

#320000
0!
0)

#325000
1!
1)
00
b1 4
08
09
b0 :
b1 A
b1 F

#330000
0!
0)

#335000
1!
b11111111 (
1)
b1 :
b11111111 E
b10 F

#340000
0!
0)

#345000
1!
1)
b10 :
b11 F

#350000
0!
0)

#355000
1!
1)
b11 :
b100 F

#360000
0!
0)

#365000
1!
1)
b100 :
b101 F

#370000
0!
0)

#375000
1!
1)
b101 :
b110 F

#380000
0!
0)

#385000
1!
1)
b110 :
b111 F

#390000
0!
0)

#395000
1!
1)
b111 :
b1000 F

#400000
0!
0)

#405000
1!
1)
b1000 :
b1001 F

#410000
0!
0)

#415000
1!
1)
b1001 :
b1010 F

#420000
0!
0$
0)
0,

#425000
1!
1)
b0 F

#430000
0!
0)

#435000
1!
b0 (
1)
b0 E

#440000
0!
0)

#445000
1!
1%
1)
1-
b1 <

#450000
0!
0)

#455000
1!
1)
b10 <

#460000
0!
0)

#465000
1!
1)
b11 <

#470000
0!
0)

#475000
1!
1)
b100 <

#480000
0!
0)

#485000
1!
1)
b101 <

#490000
0!
0)

#495000
1!
1)
b110 <

#500000
0!
0)

#505000
1!
1)
b111 <

#510000
0!
0)

#515000
1!
1)
b1000 <

#520000
0!
0)

#525000
1!
1)
b1001 <

#530000
0!
0)

#535000
1!
1)
b1010 <

#540000
0!
0)

#545000
1!
1)
11
18
1;
b1011 <

#550000
0!
0)

#555000
1!
1)
01
b1 5
08
0;
b0 <
b1 B
b1 F

#560000
0!
0)

#565000
1!
b11111111 (
1)
b1 <
b11111111 E
b10 F

#570000
0!
0)

#575000
1!
1)
b10 <
b11 F

#580000
0!
0)

#585000
1!
1)
b11 <
b100 F

#590000
0!
0)

#595000
1!
1)
b100 <
b101 F

#600000
0!
0)

#605000
1!
1)
b101 <
b110 F

#610000
0!
0)

#615000
1!
1)
b110 <
b111 F

#620000
0!
0)

#625000
1!
1)
b111 <
b1000 F

#630000
0!
0)

#635000
1!
1)
b1000 <
b1001 F

#640000
0!
0)

#645000
1!
0%
1)
0-
b1010 F

#650000
0!
0)

#655000
1!
1)
b0 F

#660000
0!
0)

#665000
1!
b0 (
1)
b0 E

#670000
0!
1%
1&
0)
1-
1.

#675000
1!
1)
b1001 <
b1 >

#680000
0!
0)

#685000
1!
1)
b1010 <
b10 >

#690000
0!
0)

#695000
1!
1)
11
18
1;
b1011 <
b11 >

#700000
0!
0)

#705000
1!
1)
01
b10 5
08
0;
b0 <
b100 >
b10 B
b1 F

#710000
0!
0)

#715000
1!
b11111111 (
1)
b1 <
b101 >
b11111111 E
b10 F

#720000
0!
0)

#725000
1!
1)
b10 <
b110 >
b11 F

#730000
0!
0)

#735000
1!
1)
b11 <
b111 >
b100 F

#740000
0!
0)

#745000
1!
1)
b100 <
b1000 >
b101 F

#750000
0!
0)

#755000
1!
1)
b101 <
b1001 >
b110 F

#760000
0!
0)

#765000
1!
1)
b110 <
b1010 >
b111 F

#770000
0!
0)

#775000
1!
1)
12
18
b111 <
1=
b1011 >
b1000 F

#780000
0!
0)

#785000
1!
1)
02
b1 6
08
b1000 <
0=
b0 >
b1 C
b1001 F

#790000
0!
0)

#795000
1!
1)
b1001 <
b1 >
b1010 F

#800000
0!
0)

#805000
1!
1)
b1010 <
b10 >
b0 F

#810000
0!
0)

#815000
1!
b0 (
1)
11
18
1;
b1011 <
b11 >
b0 E

#820000
0!
0)

#825000
1!
1)
01
b11 5
08
0;
b0 <
b100 >
b11 B
b1 F

#830000
0!
0)

#835000
1!
b11111111 (
1)
b1 <
b101 >
b11111111 E
b10 F

#840000
0!
0)

#845000
1!
1)
b10 <
b110 >
b11 F

#850000
0!
0)

#855000
1!
1)
b11 <
b111 >
b100 F

#860000
0!
0)

#865000
1!
1)
b100 <
b1000 >
b101 F

#870000
0!
0%
0&
0)
0-
0.

#875000
1!
1)
b110 F

#880000
0!
0)

#885000
1!
1)
b111 F

#890000
0!
0)

#895000
1!
1#
1%
1)
1+
1-
b101 <
b1000 F

#900000
0!
0)

#905000
1!
1)
b110 <
b1001 F

#910000
0!
0)

#915000
1!
1)
b111 <
b1010 F

#920000
0!
0)

#925000
1!
1)
b1000 <
b0 F

#930000
0!
0)

#935000
1!
1)
b1001 <

#940000
0!
0)

#945000
1!
1)
b1010 <

#950000
0!
0)

#955000
1!
1)
11
18
1;
b1011 <

#960000
0!
0)

#965000
1!
b11 (
1)
01
08
0;
b0 <
b11 E
b1 F

#970000
0!
0)

#975000
1!
1)
b1 <
b10 F

#980000
0!
0)

#985000
1!
1)
b10 <
b11 F

#990000
0!
0)

#995000
1!
1)
b11 <
b100 F

